navmazing/__init__.py
navmazing/_errors.py
navmazing/_logging.py
navmazing/_navigator.py
navmazing/_shortcuts.py
navmazing/_step.py
navmazing/py.typed
navmazing-1.3.0.dist-info/LICENSE
navmazing-1.3.0.dist-info/METADATA
navmazing-1.3.0.dist-info/WHEEL
navmazing-1.3.0.dist-info/top_level.txt
navmazing-1.3.0.dist-info/RECORD
