Metadata-Version: 2.2
Name: navmazing
Version: 1.3.0
Summary: A simple navigation framework
Author-email: Peter Savage <psavage@redhat.com>
Maintainer-email: Ronny Pfannschmidt <rpfannsc@redhat.com>
Project-URL: Project, https://github.com/RedhatQE/navmazing/
Keywords: selenium,navigation
Classifier: Development Status :: 4 - Beta
Classifier: Environment :: Console
Classifier: Intended Audience :: Developers
Classifier: Operating System :: OS Independent
Classifier: Programming Language :: Python :: 3.8
Classifier: Programming Language :: Python :: 3.9
Classifier: Programming Language :: Python :: 3.10
Classifier: Programming Language :: Python :: 3.11
Classifier: Programming Language :: Python :: 3.12
Classifier: Programming Language :: Python :: 3.13
Classifier: Topic :: Utilities
Requires-Python: >=3.8
License-File: LICENSE
